project_2/project_2.srcs/sim_1/new/model.vh
// model.vh - golden reference mirroring alu_tp2.v's combinational logic.
// Used only in testbenches for auto-checking; include inside a module body.
// No include guard: this (and alu_ops.vh) may be included in more than one
// module scope within the same simulation run, and a guard would silently
// blank out the second inclusion.

`include "alu_ops.vh"

function [7:0] golden_alu;
    input signed [7:0] a;
    input signed [7:0] b;
    input [5:0] op;
    reg [8:0] tmp;
    begin
        case (op)
            OP_ADD:  begin tmp = a + b; golden_alu = tmp[7:0]; end
            OP_SUB:  begin tmp = a - b; golden_alu = tmp[7:0]; end
            OP_AND:  golden_alu = a & b;
            OP_OR:   golden_alu = a | b;
            OP_XOR:  golden_alu = a ^ b;
            OP_SRA:  golden_alu = a >>> b;
            OP_SRL:  golden_alu = a >> b;
            OP_NOR:  golden_alu = ~(a | b);
            default: golden_alu = 8'b0;
        endcase
    end
endfunction

project_3/project_3.srcs/sources_1/new/alu_ops.vh
// Codigos = {instr[30], funct3}: tienen que coincidir con ALU_* de riscv_defs.vh
// (es lo que genera control_unit).
localparam OP_ADD  = 4'b0000;
localparam OP_SUB  = 4'b1000;
localparam OP_SLL  = 4'b0001;
localparam OP_SLT  = 4'b0010;
localparam OP_SLTU = 4'b0011;
localparam OP_XOR  = 4'b0100;
localparam OP_SRL  = 4'b0101;
localparam OP_SRA  = 4'b1101;
localparam OP_OR   = 4'b0110;
localparam OP_AND  = 4'b0111;
localparam OP_NOR  = 4'b1011;   // no es RV32I, control_unit no la genera

project_1/project_1.srcs/sources_1/new/alu_tp1.v
`timescale 1ns / 1ps
//////////////////////////////////////////////////////////////////////////////////
// Company: Universidad Nacional de Cordoba
// Engineer: Mateo Bernardi, Pablo Castilla
// 
// Create Date: 08/29/2026 10:50:54 AM
// Design Name: 
// Module Name: alu_tp1
// Project Name: TP1
// Target Devices: 
// Tool Versions: 
// Description: 
// 
// Dependencies: 
// 
// Revision:
// Revision 0.01 - File Created
// Additional Comments:
// 
//////////////////////////////////////////////////////////////////////////////////


module alu_tp1
#(
    parameter NB_DATA = 8,
    parameter NB_OP = 6
)
(
    input signed [NB_DATA-1:0] i_data_a,
    input signed [NB_DATA-1:0] i_data_b,
    input [NB_OP-1:0] i_data_op,
    output signed [NB_DATA-1:0] o_data,
    output reg o_z,
    output reg o_o   
);

`include "alu_ops.vh"

reg [NB_DATA-1 : 0] alu_result;
reg [NB_DATA:0] tmp;

always@(*) begin
    o_o   = 1'b0;
    o_z       = 1'b0;
    alu_result = {NB_DATA{1'b0}};
    case (i_data_op)
        OP_ADD: begin //ADD
                tmp          = i_data_a + i_data_b;
                alu_result = tmp[NB_DATA-1:0];
                o_o   = (i_data_a[NB_DATA-1] == i_data_b[NB_DATA-1]) &&
                               (alu_result[NB_DATA-1] != i_data_a[NB_DATA-1]);
            end

        OP_SUB: 
            begin // SUB
                tmp          = i_data_a - i_data_b;
                alu_result = tmp[NB_DATA-1:0];
                o_o   = (i_data_a[NB_DATA-1] != i_data_b[NB_DATA-1]) &&
                               (alu_result[NB_DATA-1] != i_data_a[NB_DATA-1]);
            end
        OP_AND: alu_result = i_data_a & i_data_b; //AND
        OP_OR: alu_result = i_data_a | i_data_b; //OR
        OP_XOR: alu_result = i_data_a ^ i_data_b; //XOR
        OP_SRA: alu_result = i_data_a >>> i_data_b; //SRA
        OP_SRL: alu_result = i_data_a >> i_data_b; //SRL
        OP_NOR: alu_result = ~(i_data_a | i_data_b);//A NOR B
        
        default: alu_result =  {NB_DATA{1'b0}};
    endcase
    
    o_z = (alu_result == {NB_DATA{1'b0}});
end

assign o_data = alu_result;

endmodule

TP1/TP1.srcs/sources_1/new/top.v
`timescale 1ns / 1ps
//////////////////////////////////////////////////////////////////////////////////
// Company: Universidad Nacional de Cordoba
// Engineers: Mateo Bernardi, Pablo Castilla
// 
// Create Date: 08/29/2026 10:23:43 AM
// Design Name: 
// Module Name: top
// Project Name: TP1
// Target Devices: 
// Tool Versions: 
// Description: 
// 
// Dependencies: 
// 
// Revision:
// Revision 0.01 - File Created
// Additional Comments:
// 
//////////////////////////////////////////////////////////////////////////////////

module top
#(
    parameter NB_DATA = 8,
    parameter NB_BITS = 8,
    parameter NB_OP = 6,
    parameter NB_BUTTON = 3
)
(
    input wire [NB_BITS-1:0] switch,
    input wire [NB_BUTTON-1:0] button,
    input wire i_clk,
    output signed [NB_DATA-1: 0] led,
    output f_o,
    output f_z
);

localparam BTN_DATA_A = 3'b001;
localparam BTN_DATA_B = 3'b010;
localparam BTN_DATA_OP = 3'b100;

reg [NB_DATA-1:0] alu_data_a;
reg [NB_DATA-1:0] alu_data_b;
reg [NB_OP-1:0] alu_data_op;

alu_tp1 
#(
    .NB_DATA(NB_DATA),
    .NB_OP(NB_OP)
)
u_alu
(
    .i_data_a(alu_data_a),
    .i_data_b(alu_data_b),
    .i_data_op(alu_data_op),
    .o_data(led),
    .o_z(f_z),
    .o_o(f_o)
);

always@(posedge i_clk) begin:inputs
    case(button)
    BTN_DATA_A: alu_data_a <= switch;
    BTN_DATA_B: alu_data_b <= switch;
    BTN_DATA_OP: alu_data_op <= switch [NB_OP-1:0];
    endcase
end

endmodule

TP1/TP1.srcs/sim_1/new/top_tp.v
`timescale 1ns / 1ps

module tb_top;

    parameter NB_DATA   = 8;
    parameter NB_OP     = 6;
    parameter NB_BITS   = 8;
    parameter NB_BUTTON = 3;

    parameter NUM_RANDOM_PER_OP = 20;
    parameter VERBOSE           = 0;
    
    `include "alu_ops.vh"
    `include "model.vh"

    localparam [NB_BUTTON-1:0] BTN_NONE    = 3'b000;
    localparam [NB_BUTTON-1:0] BTN_DATA_A  = 3'b001;
    localparam [NB_BUTTON-1:0] BTN_DATA_B  = 3'b010;
    localparam [NB_BUTTON-1:0] BTN_DATA_OP = 3'b100;

    reg  [NB_BITS-1:0]       switch;
    reg  [NB_BUTTON-1:0]     button;
    reg                      i_clk;
    wire signed [NB_DATA-1:0] led;
    wire                      f_o;
    wire                      f_z;

    top 
    #(
        .NB_DATA   (NB_DATA),
        .NB_BITS   (NB_BITS),
        .NB_OP     (NB_OP),
        .NB_BUTTON (NB_BUTTON)
    ) 
    uut (
        .switch (switch),
        .button (button),
        .i_clk  (i_clk),
        .led    (led),
        .f_o    (f_o),
        .f_z    (f_z)
    );

    always begin
        i_clk = 0; #10;
        i_clk = 1; #10;
    end

    integer rnd_seed   = 32'hFACADA;
    integer test_count = 0;
    integer pass_count = 0;
    integer fail_count = 0;

    reg [NB_OP-1:0] op_list [0:7];

    localparam signed [NB_DATA-1:0] MAX_POS = {1'b0, {(NB_DATA-1){1'b1}}};
    localparam signed [NB_DATA-1:0] MIN_NEG = {1'b1, {(NB_DATA-1){1'b0}}};

    task automatic press_button;
        input [NB_BUTTON-1:0] btn;
        input [NB_BITS-1:0]   value;
        begin
            @(negedge i_clk);
            switch = value;
            button = btn;
            @(posedge i_clk); 
            @(negedge i_clk);
            button = BTN_NONE;
        end
    endtask

    task automatic run_test;
        input signed [NB_DATA-1:0] a;
        input signed [NB_DATA-1:0] b;
        input        [NB_OP-1:0]   op;
        reg signed [NB_DATA-1:0] exp_data;
        reg                      exp_zero;
        reg                      exp_ovf;
        begin
            press_button(BTN_DATA_A,  a);
            press_button(BTN_DATA_B,  b);
            press_button(BTN_DATA_OP, op);
            #1;

            alu_model(a, b, op, exp_data, exp_zero, exp_ovf);

            test_count = test_count + 1;
            if (led !== exp_data || f_z !== exp_zero || f_o !== exp_ovf) begin
                fail_count = fail_count + 1;
                $display("[FAIL] #%0d op=%b A=%0d B=%0d -> led=%0d (esp %0d)  f_z=%b (esp %b)  f_o=%b (esp %b)",
                          test_count, op, a, b, led, exp_data, f_z, exp_zero, f_o, exp_ovf);
            end else begin
                pass_count = pass_count + 1;
                if (VERBOSE)
                    $display("[ OK ] #%0d op=%b A=%0d B=%0d -> led=%0d f_z=%b f_o=%b",
                              test_count, op, a, b, led, f_z, f_o);
            end
        end
    endtask

    integer i, j;

    initial begin
        $dumpfile("tb_top.vcd");
        $dumpvars(0, tb_top);

        switch = 0;
        button = BTN_NONE;

        op_list[0] = OP_ADD; op_list[1] = OP_SUB; op_list[2] = OP_AND; op_list[3] = OP_OR;
        op_list[4] = OP_XOR; op_list[5] = OP_SRA; op_list[6] = OP_SRL; op_list[7] = OP_NOR;

        @(negedge i_clk); 

        $display("==========================================================");
        $display(" TB_TOP - probando top (NB_DATA=%0d, NB_OP=%0d, NB_BITS=%0d)", NB_DATA, NB_OP, NB_BITS);
        $display("==========================================================");

        run_test(10, 20, OP_ADD);
        run_test(MAX_POS, 1, OP_ADD);
        run_test(MIN_NEG, -1, OP_ADD);

        run_test(20, 10, OP_SUB);
        run_test(MIN_NEG, 1, OP_SUB);
        run_test(MAX_POS, -1, OP_SUB);
        run_test(42, 42, OP_SUB);

        run_test(8'sb11110000, 8'sb10101010, OP_AND);
        run_test({NB_DATA{1'b1}}, {NB_DATA{1'b0}}, OP_OR);
        run_test(37, 37, OP_XOR);
        run_test({NB_DATA{1'b0}}, {NB_DATA{1'b0}}, OP_NOR);

        run_test(MIN_NEG, 1, OP_SRA);
        run_test(MIN_NEG, 1, OP_SRL);
        run_test(-1, 0, OP_SRA);

        run_test(5, 5, 6'b111111); 

        for (i = 0; i < 8; i = i + 1) begin
            for (j = 0; j < NUM_RANDOM_PER_OP; j = j + 1) begin
                if (op_list[i] == OP_SRA || op_list[i] == OP_SRL)
                    run_test($random(rnd_seed), rand_range(0, NB_DATA-1), op_list[i]);
                else
                    run_test($random(rnd_seed), $random(rnd_seed), op_list[i]);
            end
        end

        // ------------------- Resumen -------------------
        $display("==========================================================");
        $display(" %0d tests | %0d OK | %0d FALLADOS", test_count, pass_count, fail_count);
        if (fail_count == 0)
            $display(" RESULTADO: PASS");
        else
            $display(" RESULTADO: FAIL");
        $display("==========================================================");

        $finish;
    end

endmodule

TP1/TP1.sim/sim_1/behav/xsim/tb_top.vcd
$date
   Sat Aug 29 14:27:00 2026
$end

$version
  2024.1
  $dumpfile ("tb_top.vcd") 
$end

$timescale
  1ps
$end

$scope module tb_top $end
$var reg 8 ! switch [7:0] $end
$var reg 3 " button [2:0] $end
$var reg 1 # i_clk $end
$var wire 8 $ led [7:0] $end
$var wire 1 % f_o $end
$var wire 1 & f_z $end
$var integer 32 ' rnd_seed [31:0] $end
$var integer 32 ( test_count [31:0] $end
$var integer 32 ) pass_count [31:0] $end
$var integer 32 * fail_count [31:0] $end
$var integer 32 + i [31:0] $end
$var integer 32 , j [31:0] $end
$scope module uut $end
$var wire 8 - switch [7:0] $end
$var wire 3 . button [2:0] $end
$var wire 1 / i_clk $end
$var wire 8 $ led [7:0] $end
$var wire 1 % f_o $end
$var wire 1 & f_z $end
$var reg 8 0 alu_data_a [7:0] $end
$var reg 8 1 alu_data_b [7:0] $end
$var reg 6 2 alu_data_op [5:0] $end
$scope module u_alu $end
$var wire 8 3 i_data_a [7:0] $end
$var wire 8 4 i_data_b [7:0] $end
$var wire 6 5 i_data_op [5:0] $end
$var wire 8 $ o_data [7:0] $end
$var reg 1 6 o_z $end
$var reg 1 7 o_o $end
$var reg 8 8 alu_result [7:0] $end
$var reg 9 9 tmp [8:0] $end
$upscope $end
$upscope $end
$scope function rand_range $end
$upscope $end
$scope task alu_model $end
$upscope $end
$scope task press_button $end
$upscope $end
$scope task run_test $end
$upscope $end
$upscope $end
$enddefinitions $end

#0
$dumpvars
b0 !
b0 "
0#
bx $
x%
x&
b111110101100101011011010 '
b0 (
b0 )
b0 *
bx +
bx ,
b0 -
b0 .
0/
bx 0
bx 1
bx 2
bx 3
bx 4
bx 5
x6
x7
bx 8
bx 9
$end

#10000
1#
1/

#20000
0#
0/

#30000
1#
1/

#40000
b1010 !
b1 "
0#
b1010 -
b1 .
0/

#50000
1#
b0 $
0%
1&
1/
b1010 0
b1010 3
16
07
b0 8

#60000
b0 "
0#
b0 .
0/

#70000
1#
1/

#80000
b10100 !
b10 "
0#
b10100 -
b10 .
0/

#90000
1#
1/
b10100 1
b10100 4
16

#100000
b0 "
0#
b0 .
0/

#110000
1#
1/

#120000
b100000 !
b100 "
0#
b100000 -
b100 .
0/

#130000
1#
b11110 $
0&
1/
b100000 2
b100000 5
06
b11110 8
b11110 9

#140000
b0 "
0#
b0 .
0/

#141000
b1 (
b1 )

#150000
1#
1/

#160000
b1111111 !
b1 "
0#
b1111111 -
b1 .
0/

#170000
1#
b10010011 $
1%
1/
b1111111 0
b1111111 3
17
b10010011 8
b10010011 9

#180000
b0 "
0#
b0 .
0/

#190000
1#
1/

#200000
b1 !
b10 "
0#
b1 -
b10 .
0/

#210000
1#
b10000000 $
1/
b1 1
b1 4
17
b10000000 8
b10000000 9

#220000
b0 "
0#
b0 .
0/

#230000
1#
1/

#240000
b100000 !
b100 "
0#
b100000 -
b100 .
0/

#250000
1#
1/

#260000
b0 "
0#
b0 .
0/

#261000
b10 (
b10 )

#270000
1#
1/

#280000
b10000000 !
b1 "
0#
b10000000 -
b1 .
0/

#290000
1#
b10000001 $
0%
1/
b10000000 0
b10000000 3
07
b10000001 8
b110000001 9

#300000
b0 "
0#
b0 .
0/

#310000
1#
1/

#320000
b11111111 !
b10 "
0#
b11111111 -
b10 .
0/

#330000
1#
b1111111 $
1%
1/
b11111111 1
b11111111 4
17
b1111111 8
b101111111 9

#340000
b0 "
0#
b0 .
0/

#350000
1#
1/

#360000
b100000 !
b100 "
0#
b100000 -
b100 .
0/

#370000
1#
1/

#380000
b0 "
0#
b0 .
0/

#381000
b11 (
b11 )

#390000
1#
1/

#400000
b10100 !
b1 "
0#
b10100 -
b1 .
0/

#410000
1#
b10011 $
0%
1/
b10100 0
b10100 3
07
b10011 8
b10011 9

#420000
b0 "
0#
b0 .
0/

#430000
1#
1/

#440000
b1010 !
b10 "
0#
b1010 -
b10 .
0/

#450000
1#
b11110 $
1/
b1010 1
b1010 4
b11110 8
b11110 9

#460000
b0 "
0#
b0 .
0/

#470000
1#
1/

#480000
b100010 !
b100 "
0#
b100010 -
b100 .
0/

#490000
1#
b1010 $
1/
b100010 2
b100010 5
b1010 8
b1010 9

#500000
b0 "
0#
b0 .
0/

#501000
b100 (
b100 )

#510000
1#
1/

#520000
b10000000 !
b1 "
0#
b10000000 -
b1 .
0/

#530000
1#
b1110110 $
1%
1/
b10000000 0
b10000000 3
17
b1110110 8
b101110110 9

#540000
b0 "
0#
b0 .
0/

#550000
1#
1/

#560000
b1 !
b10 "
0#
b1 -
b10 .
0/

#570000
1#
b1111111 $
1/
b1 1
b1 4
17
b1111111 8
b101111111 9

#580000
b0 "
0#
b0 .
0/

#590000
1#
1/

#600000
b100010 !
b100 "
0#
b100010 -
b100 .
0/

#610000
1#
1/

#620000
b0 "
0#
b0 .
0/

#621000
b101 (
b101 )

#630000
1#
1/

#640000
b1111111 !
b1 "
0#
b1111111 -
b1 .
0/

#650000
1#
b1111110 $
0%
1/
b1111111 0
b1111111 3
07
b1111110 8
b1111110 9

#660000
b0 "
0#
b0 .
0/

#670000
1#
1/

#680000
b11111111 !
b10 "
0#
b11111111 -
b10 .
0/

#690000
1#
b10000000 $
1%
1/
b11111111 1
b11111111 4
17
b10000000 8
b10000000 9

#700000
b0 "
0#
b0 .
0/

#710000
1#
1/

#720000
b100010 !
b100 "
0#
b100010 -
b100 .
0/

#730000
1#
1/

#740000
b0 "
0#
b0 .
0/

#741000
b110 (
b110 )

#750000
1#
1/

#760000
b101010 !
b1 "
0#
b101010 -
b1 .
0/

#770000
1#
b101011 $
0%
1/
b101010 0
b101010 3
07
b101011 8
b101011 9

#780000
b0 "
0#
b0 .
0/

#790000
1#
1/

#800000
b10 "
0#
b10 .
0/

#810000
1#
b0 $
1&
1/
b101010 1
b101010 4
16
b0 8
b0 9

#820000
b0 "
0#
b0 .
0/

#830000
1#
1/

#840000
b100010 !
b100 "
0#
b100010 -
b100 .
0/

#850000
1#
1/

#860000
b0 "
0#
b0 .
0/

#861000
b111 (
b111 )

#870000
1#
1/

#880000
b11110000 !
b1 "
0#
b11110000 -
b1 .
0/

#890000
1#
b11000110 $
0&
1/
b11110000 0
b11110000 3
06
b11000110 8
b111000110 9

#900000
b0 "
0#
b0 .
0/

#910000
1#
1/

#920000
b10101010 !
b10 "
0#
b10101010 -
b10 .
0/

#930000
1#
b1000110 $
1/
b10101010 1
b10101010 4
b1000110 8
b1000110 9

#940000
b0 "
0#
b0 .
0/

#950000
1#
1/

#960000
b100100 !
b100 "
0#
b100100 -
b100 .
0/

#970000
1#
b10100000 $
1/
b100100 2
b100100 5
b10100000 8

#980000
b0 "
0#
b0 .
0/

#981000
b1000 (
b1000 )

#990000
1#
1/

#1000000
b11111111 !
b1 "
0#
b11111111 -
b1 .
0/

#1010000
1#
b10101010 $
1/
b11111111 0
b11111111 3
b10101010 8

#1020000
b0 "
0#
b0 .
0/

#1030000
1#
1/

#1040000
b0 !
b10 "
0#
b0 -
b10 .
0/

#1050000
1#
b0 $
1&
1/
b0 1
b0 4
16
b0 8

#1060000
b0 "
0#
b0 .
0/

#1070000
1#
1/

#1080000
b100101 !
b100 "
0#
b100101 -
b100 .
0/

#1090000
1#
b11111111 $
0&
1/
b100101 2
b100101 5
06
b11111111 8

#1100000
b0 "
0#
b0 .
0/

#1101000
b1001 (
b1001 )

#1110000
1#
1/

#1120000
b1 "
0#
b1 .
0/

#1130000
1#
b100101 $
1/
b100101 0
b100101 3
b100101 8

#1140000
b0 "
0#
b0 .
0/

#1150000
1#
1/

#1160000
b10 "
0#
b10 .
0/

#1170000
1#
1/
b100101 1
b100101 4
b100101 8

#1180000
b0 "
0#
b0 .
0/

#1190000
1#
1/

#1200000
b100110 !
b100 "
0#
b100110 -
b100 .
0/

#1210000
1#
b0 $
1&
1/
b100110 2
b100110 5
16
b0 8

#1220000
b0 "
0#
b0 .
0/

#1221000
b1010 (
b1010 )

#1230000
1#
1/

#1240000
b0 !
b1 "
0#
b0 -
b1 .
0/

#1250000
1#
b100101 $
0&
1/
b0 0
b0 3
06
b100101 8

#1260000
b0 "
0#
b0 .
0/

#1270000
1#
1/

#1280000
b10 "
0#
b10 .
0/

#1290000
1#
b0 $
1&
1/
b0 1
b0 4
16
b0 8

#1300000
b0 "
0#
b0 .
0/

#1310000
1#
1/

#1320000
b100111 !
b100 "
0#
b100111 -
b100 .
0/

#1330000
1#
b11111111 $
0&
1/
b100111 2
b100111 5
06
b11111111 8

#1340000
b0 "
0#
b0 .
0/

#1341000
b1011 (
b1011 )

#1350000
1#
1/

#1360000
b10000000 !
b1 "
0#
b10000000 -
b1 .
0/

#1370000
1#
b1111111 $
1/
b10000000 0
b10000000 3
b1111111 8

#1380000
b0 "
0#
b0 .
0/

#1390000
1#
1/

#1400000
b1 !
b10 "
0#
b1 -
b10 .
0/

#1410000
1#
b1111110 $
1/
b1 1
b1 4
b1111110 8

#1420000
b0 "
0#
b0 .
0/

#1430000
1#
1/

#1440000
b11 !
b100 "
0#
b11 -
b100 .
0/

#1450000
1#
b11000000 $
1/
b11 2
b11 5
b11000000 8

#1460000
b0 "
0#
b0 .
0/

#1461000
b1100 (
b1100 )

#1470000
1#
1/

#1480000
b10000000 !
b1 "
0#
b10000000 -
b1 .
0/

#1490000
1#
1/

#1500000
b0 "
0#
b0 .
0/

#1510000
1#
1/

#1520000
b1 !
b10 "
0#
b1 -
b10 .
0/

#1530000
1#
1/

#1540000
b0 "
0#
b0 .
0/

#1550000
1#
1/

#1560000
b10 !
b100 "
0#
b10 -
b100 .
0/

#1570000
1#
b1000000 $
1/
b10 2
b10 5
b1000000 8

#1580000
b0 "
0#
b0 .
0/

#1581000
b1101 (
b1101 )

#1590000
1#
1/

#1600000
b11111111 !
b1 "
0#
b11111111 -
b1 .
0/

#1610000
1#
b1111111 $
1/
b11111111 0
b11111111 3
b1111111 8

#1620000
b0 "
0#
b0 .
0/

#1630000
1#
1/

#1640000
b0 !
b10 "
0#
b0 -
b10 .
0/

#1650000
1#
b11111111 $
1/
b0 1
b0 4
b11111111 8

#1660000
b0 "
0#
b0 .
0/

#1670000
1#
1/

#1680000
b11 !
b100 "
0#
b11 -
b100 .
0/

#1690000
1#
1/
b11 2
b11 5
b11111111 8

#1700000
b0 "
0#
b0 .
0/

#1701000
b1110 (
b1110 )

#1710000
1#
1/

#1720000
b101 !
b1 "
0#
b101 -
b1 .
0/

#1730000
1#
b101 $
1/
b101 0
b101 3
b101 8

#1740000
b0 "
0#
b0 .
0/

#1750000
1#
1/

#1760000
b10 "
0#
b10 .
0/

#1770000
1#
b0 $
1&
1/
b101 1
b101 4
16
b0 8

#1780000
b0 "
0#
b0 .
0/

#1790000
1#
1/

#1800000
b111111 !
b100 "
0#
b111111 -
b100 .
0/

#1810000
1#
1/
b111111 2
b111111 5
16

#1820000
b0 "
0#
b0 .
0/

#1821000
b1111 (
b1111 )
b0 +
b0 ,

#1830000
1#
1/

#1840000
b10011111 !
b1 "
0#
b10011111 -
b1 .
0/

#1850000
1#
1/
b10011111 0
b10011111 3
16

#1860000
b0 "
0#
b0 .
0/

#1870000
1#
1/

#1880000
b10101001 !
b10 "
0#
b10101001 -
b10 .
0/

#1890000
1#
1/
b10101001 1
b10101001 4
16

#1900000
b0 "
0#
b0 .
0/

#1910000
1#
1/

#1920000
b100000 !
b100 "
0#
b100000 -
b100 .
0/

#1930000
1#
b1001000 $
1%
0&
1/
b100000 2
b100000 5
06
17
b1001000 8
b101001000 9

#1940000
b0 "
0#
b0 .
0/

#1941000
b10000 (
b10000 )
b1 ,

#1950000
1#
1/

#1960000
b1101000 !
b1 "
0#
b1101000 -
b1 .
0/

#1970000
1#
b10001 $
0%
1/
b1101000 0
b1101000 3
07
b10001 8
b10001 9

#1980000
b0 "
0#
b0 .
0/

#1990000
1#
1/

#2000000
b11001110 !
b10 "
0#
b11001110 -
b10 .
0/

#2010000
1#
b110110 $
1/
b11001110 1
b11001110 4
b110110 8
b110110 9

#2020000
b0 "
0#
b0 .
0/

#2030000
1#
1/

#2040000
b100000 !
b100 "
0#
b100000 -
b100 .
0/

#2050000
1#
1/

#2060000
b0 "
0#
b0 .
0/

#2061000
b10001 (
b10001 )
b10 ,

#2070000
1#
1/

#2080000
b111000 !
b1 "
0#
b111000 -
b1 .
0/

#2090000
1#
b110 $
1/
b111000 0
b111000 3
b110 8
b110 9

#2100000
b0 "
0#
b0 .
0/

#2110000
1#
1/

#2120000
b1110000 !
b10 "
0#
b1110000 -
b10 .
0/

#2130000
1#
b10101000 $
1%
1/
b1110000 1
b1110000 4
17
b10101000 8
b10101000 9

#2140000
b0 "
0#
b0 .
0/

#2150000
1#
1/

#2160000
b100000 !
b100 "
0#
b100000 -
b100 .
0/

#2170000
1#
1/

#2180000
b0 "
0#
b0 .
0/

#2181000
b10010 (
b10010 )
b11 ,

#2190000
1#
1/

#2200000
b110110 !
b1 "
0#
b110110 -
b1 .
0/

#2210000
1#
b10100110 $
1/
b110110 0
b110110 3
17
b10100110 8
b10100110 9

#2220000
b0 "
0#
b0 .
0/

#2230000
1#
1/

#2240000
b11101010 !
b10 "
0#
b11101010 -
b10 .
0/

#2250000
1#
b100000 $
0%
1/
b11101010 1
b11101010 4
07
b100000 8
b100000 9

#2260000
b0 "
0#
b0 .
0/

#2270000
1#
1/

#2280000
b100000 !
b100 "
0#
b100000 -
b100 .
0/

#2290000
1#
1/

#2300000
b0 "
0#
b0 .
0/

#2301000
b10011 (
b10011 )
b100 ,

#2310000
1#
1/

#2320000
b10110101 !
b1 "
0#
b10110101 -
b1 .
0/

#2330000
1#
b10011111 $
1/
b10110101 0
b10110101 3
b10011111 8
b110011111 9

#2340000
b0 "
0#
b0 .
0/

#2350000
1#
1/

#2360000
b1010010 !
b10 "
0#
b1010010 -
b10 .
0/

#2370000
1#
b111 $
1/
b1010010 1
b1010010 4
b111 8
b111 9

#2380000
b0 "
0#
b0 .
0/

#2390000
1#
1/

#2400000
b100000 !
b100 "
0#
b100000 -
b100 .
0/

#2410000
1#
1/

#2420000
b0 "
0#
b0 .
0/

#2421000
b10100 (
b10100 )
b101 ,

#2430000
1#
1/

#2440000
b10011000 !
b1 "
0#
b10011000 -
b1 .
0/

#2450000
1#
b11101010 $
1/
b10011000 0
b10011000 3
b11101010 8
b111101010 9

#2460000
b0 "
0#
b0 .
0/

#2470000
1#
1/

#2480000
b10010011 !
b10 "
0#
b10010011 -
b10 .
0/

#2490000
1#
b101011 $
1%
1/
b10010011 1
b10010011 4
17
b101011 8
b100101011 9

#2500000
b0 "
0#
b0 .
0/

#2510000
1#
1/

#2520000
b100000 !
b100 "
0#
b100000 -
b100 .
0/

#2530000
1#
1/

#2540000
b0 "
0#
b0 .
0/

#2541000
b10101 (
b10101 )
b110 ,

#2550000
1#
1/

#2560000
b111001 !
b1 "
0#
b111001 -
b1 .
0/

#2570000
1#
b11001100 $
0%
1/
b111001 0
b111001 3
07
b11001100 8
b111001100 9

#2580000
b0 "
0#
b0 .
0/

#2590000
1#
1/

#2600000
b10010101 !
b10 "
0#
b10010101 -
b10 .
0/

#2610000
1#
b11001110 $
1/
b10010101 1
b10010101 4
b11001110 8
b111001110 9

#2620000
b0 "
0#
b0 .
0/

#2630000
1#
1/

#2640000
b100000 !
b100 "
0#
b100000 -
b100 .
0/

#2650000
1#
1/

#2660000
b0 "
0#
b0 .
0/

#2661000
b10110 (
b10110 )
b111 ,

#2670000
1#
1/

#2680000
b10111 !
b1 "
0#
b10111 -
b1 .
0/

#2690000
1#
b10101100 $
1/
b10111 0
b10111 3
b10101100 8
b110101100 9

#2700000
b0 "
0#
b0 .
0/

#2710000
1#
1/

#2720000
b1001001 !
b10 "
0#
b1001001 -
b10 .
0/

#2730000
1#
b1100000 $
1/
b1001001 1
b1001001 4
b1100000 8
b1100000 9

#2740000
b0 "
0#
b0 .
0/

#2750000
1#
1/

#2760000
b100000 !
b100 "
0#
b100000 -
b100 .
0/

#2770000
1#
1/

#2780000
b0 "
0#
b0 .
0/

#2781000
b10111 (
b10111 )
b1000 ,

#2790000
1#
1/

#2800000
b1001000 !
b1 "
0#
b1001000 -
b1 .
0/

#2810000
1#
b10010001 $
1%
1/
b1001000 0
b1001000 3
17
b10010001 8
b10010001 9

#2820000
b0 "
0#
b0 .
0/

#2830000
1#
1/

#2840000
b11100011 !
b10 "
0#
b11100011 -
b10 .
0/

#2850000
1#
b101011 $
0%
1/
b11100011 1
b11100011 4
07
b101011 8
b101011 9

#2860000
b0 "
0#
b0 .
0/

#2870000
1#
1/

#2880000
b100000 !
b100 "
0#
b100000 -
b100 .
0/

#2890000
1#
1/

#2900000
b0 "
0#
b0 .
0/

#2901000
b11000 (
b11000 )
b1001 ,

#2910000
1#
1/

#2920000
b10010 !
b1 "
0#
b10010 -
b1 .
0/

#2930000
1#
b11110101 $
1/
b10010 0
b10010 3
b11110101 8
b111110101 9

#2940000
b0 "
0#
b0 .
0/

#2950000
1#
1/

#2960000
b11100010 !
b10 "
0#
b11100010 -
b10 .
0/

#2970000
1#
b11110100 $
1/
b11100010 1
b11100010 4
b11110100 8
b111110100 9

#2980000
b0 "
0#
b0 .
0/

#2990000
1#
1/

#3000000
b100000 !
b100 "
0#
b100000 -
b100 .
0/

#3010000
1#
1/

#3020000
b0 "
0#
b0 .
0/

#3021000
b11001 (
b11001 )
b1010 ,

#3030000
1#
1/

#3040000
b11010111 !
b1 "
0#
b11010111 -
b1 .
0/

#3050000
1#
b10111001 $
1/
b11010111 0
b11010111 3
b10111001 8
b110111001 9

#3060000
b0 "
0#
b0 .
0/

#3070000
1#
1/

#3080000
b10110001 !
b10 "
0#
b10110001 -
b10 .
0/

#3090000
1#
b10001000 $
1/
b10110001 1
b10110001 4
b10001000 8
b110001000 9

#3100000
b0 "
0#
b0 .
0/

#3110000
1#
1/

#3120000
b100000 !
b100 "
0#
b100000 -
b100 .
0/

#3130000
1#
1/

#3140000
b0 "
0#
b0 .
0/

#3141000
b11010 (
b11010 )
b1011 ,

#3150000
1#
1/

#3160000
b10100001 !
b1 "
0#
b10100001 -
b1 .
0/

#3170000
1#
b1010010 $
1%
1/
b10100001 0
b10100001 3
17
b1010010 8
b101010010 9

#3180000
b0 "
0#
b0 .
0/

#3190000
1#
1/

#3200000
b111101 !
b10 "
0#
b111101 -
b10 .
0/

#3210000
1#
b11011110 $
0%
1/
b111101 1
b111101 4
07
b11011110 8
b111011110 9

#3220000
b0 "
0#
b0 .
0/

#3230000
1#
1/

#3240000
b100000 !
b100 "
0#
b100000 -
b100 .
0/

#3250000
1#
1/

#3260000
b0 "
0#
b0 .
0/

#3261000
b11011 (
b11011 )
b1100 ,

#3270000
1#
1/

#3280000
b11001010 !
b1 "
0#
b11001010 -
b1 .
0/

#3290000
1#
b111 $
1/
b11001010 0
b11001010 3
b111 8
b111 9

#3300000
b0 "
0#
b0 .
0/

#3310000
1#
1/

#3320000
b110010 !
b10 "
0#
b110010 -
b10 .
0/

#3330000
1#
b11111100 $
1/
b110010 1
b110010 4
b11111100 8
b111111100 9

#3340000
b0 "
0#
b0 .
0/

#3350000
1#
1/

#3360000
b100000 !
b100 "
0#
b100000 -
b100 .
0/

#3370000
1#
1/

#3380000
b0 "
0#
b0 .
0/

#3381000
b11100 (
b11100 )
b1101 ,

#3390000
1#
1/

#3400000
b10101010 !
b1 "
0#
b10101010 -
b1 .
0/

#3410000
1#
b11011100 $
1/
b10101010 0
b10101010 3
b11011100 8
b111011100 9

#3420000
b0 "
0#
b0 .
0/

#3430000
1#
1/

#3440000
b11100110 !
b10 "
0#
b11100110 -
b10 .
0/

#3450000
1#
b10010000 $
1/
b11100110 1
b11100110 4
b10010000 8
b110010000 9

#3460000
b0 "
0#
b0 .
0/

#3470000
1#
1/

