project_1/project_1.srcs/sim_1/new/model.vh
function automatic integer rand_range;
    input integer lo;
    input integer hi;
    reg [31:0] draw;
    begin
        draw = $random(rnd_seed);
        rand_range = lo + (draw % (hi - lo + 1));
    end
endfunction
task automatic alu_model;
    input  signed [NB_DATA-1:0] a;
    input  signed [NB_DATA-1:0] b;
    input         [NB_OP-1:0]   op;
    output signed [NB_DATA-1:0] data;
    output                      zero;
    output                      ovf;
    reg [NB_DATA:0] ext; 
    begin
        ovf  = 1'b0;
        data = {NB_DATA{1'b0}};
        case (op)
            OP_ADD: begin
                ext  = a + b;
                data = ext[NB_DATA-1:0];
                ovf  = (a[NB_DATA-1] == b[NB_DATA-1]) &&
                       (data[NB_DATA-1] != a[NB_DATA-1]);
            end
            OP_SUB: begin
                ext  = a - b;
                data = ext[NB_DATA-1:0];
                ovf  = (a[NB_DATA-1] != b[NB_DATA-1]) &&
                       (data[NB_DATA-1] != a[NB_DATA-1]);
            end
            OP_AND:  data = a & b;
            OP_OR :  data = a | b;
            OP_XOR:  data = a ^ b;
            OP_SRA:  data = a >>> b;
            OP_SRL:  data = a >> b;
            OP_NOR:  data = ~(a | b);
            default: data = {NB_DATA{1'b0}};
        endcase
        zero = (data == {NB_DATA{1'b0}});
    end
endtask

project_1/project_1.srcs/sources_1/new/alu_ops.vh
localparam OP_ADD = 6'b100000;
localparam OP_SUB = 6'b100010;
localparam OP_AND = 6'b100100;
localparam OP_OR  = 6'b100101;
localparam OP_XOR = 6'b100110;
localparam OP_SRA = 6'b000011;
localparam OP_SRL = 6'b000010;
localparam OP_NOR = 6'b100111;

project_1/project_1.srcs/sources_1/new/alu_tp1.v
`timescale 1ns / 1ps
//////////////////////////////////////////////////////////////////////////////////
// Company: Universidad Nacional de Cordoba
// Engineer: Mateo Bernardi, Pablo Castilla
// 
// Create Date: 08/29/2026 10:50:54 AM
// Design Name: 
// Module Name: alu_tp1
// Project Name: TP1
// Target Devices: 
// Tool Versions: 
// Description: 
// 
// Dependencies: 
// 
// Revision:
// Revision 0.01 - File Created
// Additional Comments:
// 
//////////////////////////////////////////////////////////////////////////////////


module alu_tp1
#(
    parameter NB_DATA = 8,
    parameter NB_OP = 6
)
(
    input signed [NB_DATA-1:0] i_data_a,
    input signed [NB_DATA-1:0] i_data_b,
    input [NB_OP-1:0] i_data_op,
    output signed [NB_DATA-1:0] o_data,
    output reg o_z,
    output reg o_o   
);

`include "alu_ops.vh"

reg [NB_DATA-1 : 0] alu_result;
reg [NB_DATA:0] tmp;

always@(*) begin
    o_o   = 1'b0;
    o_z       = 1'b0;
    alu_result = {NB_DATA{1'b0}};
    case (i_data_op)
        OP_ADD: begin //ADD
                tmp          = i_data_a + i_data_b;
                alu_result = tmp[NB_DATA-1:0];
                o_o   = (i_data_a[NB_DATA-1] == i_data_b[NB_DATA-1]) &&
                               (alu_result[NB_DATA-1] != i_data_a[NB_DATA-1]);
            end

        OP_SUB: 
            begin // SUB
                tmp          = i_data_a - i_data_b;
                alu_result = tmp[NB_DATA-1:0];
                o_o   = (i_data_a[NB_DATA-1] != i_data_b[NB_DATA-1]) &&
                               (alu_result[NB_DATA-1] != i_data_a[NB_DATA-1]);
            end
        OP_AND: alu_result = i_data_a & i_data_b; //AND
        OP_OR: alu_result = i_data_a | i_data_b; //OR
        OP_XOR: alu_result = i_data_a ^ i_data_b; //XOR
        OP_SRA: alu_result = i_data_a >>> i_data_b; //SRA
        OP_SRL: alu_result = i_data_a >> i_data_b; //SRL
        OP_NOR: alu_result = ~(i_data_a | i_data_b);//A NOR B
        
        default: alu_result =  {NB_DATA{1'b0}};
    endcase
    
    o_z = (alu_result == {NB_DATA{1'b0}});
end

assign o_data = alu_result;

endmodule

TP1/TP1.srcs/sources_1/new/top.v
`timescale 1ns / 1ps
//////////////////////////////////////////////////////////////////////////////////
// Company: Universidad Nacional de Cordoba
// Engineers: Mateo Bernardi, Pablo Castilla
// 
// Create Date: 08/29/2026 10:23:43 AM
// Design Name: 
// Module Name: top
// Project Name: TP1
// Target Devices: 
// Tool Versions: 
// Description: 
// 
// Dependencies: 
// 
// Revision:
// Revision 0.01 - File Created
// Additional Comments:
// 
//////////////////////////////////////////////////////////////////////////////////

module top
#(
    parameter NB_DATA = 8,
    parameter NB_BITS = 8,
    parameter NB_OP = 6,
    parameter NB_BUTTON = 3
)
(
    input wire [NB_BITS-1:0] switch,
    input wire [NB_BUTTON-1:0] button,
    input wire i_clk,
    output reg signed [NB_DATA-1: 0] led,
    output reg f_o,
    output reg f_z
);

localparam BTN_DATA_A = 3'b001;
localparam BTN_DATA_B = 3'b010;
localparam BTN_DATA_OP = 3'b100;

reg [NB_DATA-1:0] alu_data_a;
reg [NB_DATA-1:0] alu_data_b;
reg [NB_OP-1:0] alu_data_op;

wire signed [NB_DATA-1:0] alu_out_data;
wire                      alu_out_z;
wire                      alu_out_o;

alu_tp1 
#(
    .NB_DATA(NB_DATA),
    .NB_OP(NB_OP)
)
u_alu
(
    .i_data_a(alu_data_a),
    .i_data_b(alu_data_b),
    .i_data_op(alu_data_op),
    .o_data(alu_out_data),
    .o_z(alu_out_z),
    .o_o(alu_out_o)
);

reg op_loaded;

always@(posedge i_clk) begin:inputs
    case(button)
    BTN_DATA_A: alu_data_a <= switch;
    BTN_DATA_B: alu_data_b <= switch;
    BTN_DATA_OP: alu_data_op <= switch [NB_OP-1:0];
    endcase
    op_loaded <= (button == BTN_DATA_OP);   // <-- esto falta
end

always@(posedge i_clk) begin: outputs
    if (op_loaded) begin
        led <= alu_out_data;
        f_z <= alu_out_z;
        f_o <= alu_out_o;
    end
end

endmodule

TP1/TP1.srcs/sim_1/new/top_tp.v
`timescale 1ns / 1ps

module tb_top;

    parameter NB_DATA   = 8;
    parameter NB_OP     = 6;
    parameter NB_BITS   = 8;
    parameter NB_BUTTON = 3;

    parameter NUM_RANDOM_PER_OP = 20;
    parameter VERBOSE           = 0;
    
    `include "alu_ops.vh"
    `include "model.vh"

    localparam [NB_BUTTON-1:0] BTN_NONE    = 3'b000;
    localparam [NB_BUTTON-1:0] BTN_DATA_A  = 3'b001;
    localparam [NB_BUTTON-1:0] BTN_DATA_B  = 3'b010;
    localparam [NB_BUTTON-1:0] BTN_DATA_OP = 3'b100;

    reg  [NB_BITS-1:0]       switch;
    reg  [NB_BUTTON-1:0]     button;
    reg                      i_clk;
    wire signed [NB_DATA-1:0] led;
    wire                      f_o;
    wire                      f_z;

    top 
    #(
        .NB_DATA   (NB_DATA),
        .NB_BITS   (NB_BITS),
        .NB_OP     (NB_OP),
        .NB_BUTTON (NB_BUTTON)
    ) 
    uut (
        .switch (switch),
        .button (button),
        .i_clk  (i_clk),
        .led    (led),
        .f_o    (f_o),
        .f_z    (f_z)
    );

    always begin
        i_clk = 0; #10;
        i_clk = 1; #10;
    end

    integer rnd_seed   = 32'hFACADA;
    integer test_count = 0;
    integer pass_count = 0;
    integer fail_count = 0;

    reg [NB_OP-1:0] op_list [0:7];

    localparam signed [NB_DATA-1:0] MAX_POS = {1'b0, {(NB_DATA-1){1'b1}}};
    localparam signed [NB_DATA-1:0] MIN_NEG = {1'b1, {(NB_DATA-1){1'b0}}};

    task automatic press_button;
        input [NB_BUTTON-1:0] btn;
        input [NB_BITS-1:0]   value;
        begin
            @(negedge i_clk);
            switch = value;
            button = btn;
            @(posedge i_clk); 
            @(negedge i_clk);
            button = BTN_NONE;
        end
    endtask

    task automatic run_test;
        input signed [NB_DATA-1:0] a;
        input signed [NB_DATA-1:0] b;
        input        [NB_OP-1:0]   op;
        reg signed [NB_DATA-1:0] exp_data;
        reg                      exp_zero;
        reg                      exp_ovf;
        begin
            press_button(BTN_DATA_A,  a);
            press_button(BTN_DATA_B,  b);
            press_button(BTN_DATA_OP, op);
            #1;

            alu_model(a, b, op, exp_data, exp_zero, exp_ovf);

            test_count = test_count + 1;
            if (led !== exp_data || f_z !== exp_zero || f_o !== exp_ovf) begin
                fail_count = fail_count + 1;
                $display("[FAIL] #%0d op=%b A=%0d B=%0d -> led=%0d (esp %0d)  f_z=%b (esp %b)  f_o=%b (esp %b)",
                          test_count, op, a, b, led, exp_data, f_z, exp_zero, f_o, exp_ovf);
            end else begin
                pass_count = pass_count + 1;
                if (VERBOSE)
                    $display("[ OK ] #%0d op=%b A=%0d B=%0d -> led=%0d f_z=%b f_o=%b",
                              test_count, op, a, b, led, f_z, f_o);
            end
        end
    endtask

    integer i, j;

    initial begin
        $dumpfile("tb_top.vcd");
        $dumpvars(0, tb_top);

        switch = 0;
        button = BTN_NONE;

        op_list[0] = OP_ADD; op_list[1] = OP_SUB; op_list[2] = OP_AND; op_list[3] = OP_OR;
        op_list[4] = OP_XOR; op_list[5] = OP_SRA; op_list[6] = OP_SRL; op_list[7] = OP_NOR;

        @(negedge i_clk); 

        $display("==========================================================");
        $display(" TB_TOP - probando top (NB_DATA=%0d, NB_OP=%0d, NB_BITS=%0d)", NB_DATA, NB_OP, NB_BITS);
        $display("==========================================================");

        run_test(10, 20, OP_ADD);
        run_test(MAX_POS, 1, OP_ADD);
        run_test(MIN_NEG, -1, OP_ADD);

        run_test(20, 10, OP_SUB);
        run_test(MIN_NEG, 1, OP_SUB);
        run_test(MAX_POS, -1, OP_SUB);
        run_test(42, 42, OP_SUB);

        run_test(8'sb11110000, 8'sb10101010, OP_AND);
        run_test({NB_DATA{1'b1}}, {NB_DATA{1'b0}}, OP_OR);
        run_test(37, 37, OP_XOR);
        run_test({NB_DATA{1'b0}}, {NB_DATA{1'b0}}, OP_NOR);

        run_test(MIN_NEG, 1, OP_SRA);
        run_test(MIN_NEG, 1, OP_SRL);
        run_test(-1, 0, OP_SRA);

        run_test(5, 5, 6'b111111); 

        for (i = 0; i < 8; i = i + 1) begin
            for (j = 0; j < NUM_RANDOM_PER_OP; j = j + 1) begin
                if (op_list[i] == OP_SRA || op_list[i] == OP_SRL)
                    run_test($random(rnd_seed), rand_range(0, NB_DATA-1), op_list[i]);
                else
                    run_test($random(rnd_seed), $random(rnd_seed), op_list[i]);
            end
        end

        // ------------------- Resumen -------------------
        $display("==========================================================");
        $display(" %0d tests | %0d OK | %0d FALLADOS", test_count, pass_count, fail_count);
        if (fail_count == 0)
            $display(" RESULTADO: PASS");
        else
            $display(" RESULTADO: FAIL");
        $display("==========================================================");

        $finish;
    end

endmodule

TP1/TP1.sim/sim_1/behav/xsim/tb_top.vcd
$date
   Sat Aug 29 15:04:54 2026
$end

$version
  2024.1
  $dumpfile ("tb_top.vcd") 
$end

$timescale
  1ps
$end

$scope module tb_top $end
$var reg 8 ! switch [7:0] $end
$var reg 3 " button [2:0] $end
$var reg 1 # i_clk $end
$var wire 8 $ led [7:0] $end
$var wire 1 % f_o $end
$var wire 1 & f_z $end
$var integer 32 ' rnd_seed [31:0] $end
$var integer 32 ( test_count [31:0] $end
$var integer 32 ) pass_count [31:0] $end
$var integer 32 * fail_count [31:0] $end
$var integer 32 + i [31:0] $end
$var integer 32 , j [31:0] $end
$scope module uut $end
$var wire 8 - switch [7:0] $end
$var wire 3 . button [2:0] $end
$var wire 1 / i_clk $end
$var reg 8 0 led [7:0] $end
$var reg 1 1 f_o $end
$var reg 1 2 f_z $end
$var reg 8 3 alu_data_a [7:0] $end
$var reg 8 4 alu_data_b [7:0] $end
$var reg 6 5 alu_data_op [5:0] $end
$var wire 8 6 alu_out_data [7:0] $end
$var wire 1 7 alu_out_z $end
$var wire 1 8 alu_out_o $end
$var reg 1 9 op_loaded $end
$scope module u_alu $end
$var wire 8 : i_data_a [7:0] $end
$var wire 8 ; i_data_b [7:0] $end
$var wire 6 < i_data_op [5:0] $end
$var wire 8 6 o_data [7:0] $end
$var reg 1 = o_z $end
$var reg 1 > o_o $end
$var reg 8 ? alu_result [7:0] $end
$var reg 9 @ tmp [8:0] $end
$upscope $end
$upscope $end
$scope function rand_range $end
$upscope $end
$scope task alu_model $end
$upscope $end
$scope task press_button $end
$upscope $end
$scope task run_test $end
$upscope $end
$upscope $end
$enddefinitions $end

#0
$dumpvars
b0 !
b0 "
0#
bx $
x%
x&
b111110101100101011011010 '
b0 (
b0 )
b0 *
bx +
bx ,
b0 -
b0 .
0/
bx 0
x1
x2
bx 3
bx 4
bx 5
bx 6
x7
x8
x9
bx :
bx ;
bx <
x=
x>
bx ?
bx @
$end

#10000
1#
1/
09

#20000
0#
0/

#30000
1#
1/

#40000
b1010 !
b1 "
0#
b1010 -
b1 .
0/

#50000
1#
1/
b1010 3
b0 6
17
08
b1010 :
1=
0>
b0 ?

#60000
b0 "
0#
b0 .
0/

#70000
1#
1/

#80000
b10100 !
b10 "
0#
b10100 -
b10 .
0/

#90000
1#
1/
b10100 4
b10100 ;
1=

#100000
b0 "
0#
b0 .
0/

#110000
1#
1/

#120000
b100000 !
b100 "
0#
b100000 -
b100 .
0/

#130000
1#
1/
b100000 5
b11110 6
07
19
b100000 <
0=
b11110 ?
b11110 @

#140000
b0 "
0#
b0 .
0/

#150000
1#
b11110 $
0%
0&
1/
b11110 0
01
02
09

#160000
0#
0/

#161000
b1 (
b1 )

#170000
1#
1/

#180000
b1111111 !
b1 "
0#
b1111111 -
b1 .
0/

#190000
1#
1/
b1111111 3
b10010011 6
18
b1111111 :
1>
b10010011 ?
b10010011 @

#200000
b0 "
0#
b0 .
0/

#210000
1#
1/

#220000
b1 !
b10 "
0#
b1 -
b10 .
0/

#230000
1#
1/
b1 4
b10000000 6
b1 ;
1>
b10000000 ?
b10000000 @

#240000
b0 "
0#
b0 .
0/

#250000
1#
1/

#260000
b100000 !
b100 "
0#
b100000 -
b100 .
0/

#270000
1#
1/
19

#280000
b0 "
0#
b0 .
0/

#290000
1#
b10000000 $
1%
1/
b10000000 0
11
09

#300000
0#
0/

#301000
b10 (
b10 )

#310000
1#
1/

#320000
b10000000 !
b1 "
0#
b10000000 -
b1 .
0/

#330000
1#
1/
b10000000 3
b10000001 6
08
b10000000 :
0>
b10000001 ?
b110000001 @

#340000
b0 "
0#
b0 .
0/

#350000
1#
1/

#360000
b11111111 !
b10 "
0#
b11111111 -
b10 .
0/

#370000
1#
1/
b11111111 4
b1111111 6
18
b11111111 ;
1>
b1111111 ?
b101111111 @

#380000
b0 "
0#
b0 .
0/

#390000
1#
1/

#400000
b100000 !
b100 "
0#
b100000 -
b100 .
0/

#410000
1#
1/
19

#420000
b0 "
0#
b0 .
0/

#430000
1#
b1111111 $
1/
b1111111 0
09

#440000
0#
0/

#441000
b11 (
b11 )

#450000
1#
1/

#460000
b10100 !
b1 "
0#
b10100 -
b1 .
0/

#470000
1#
1/
b10100 3
b10011 6
08
b10100 :
0>
b10011 ?
b10011 @

#480000
b0 "
0#
b0 .
0/

#490000
1#
1/

#500000
b1010 !
b10 "
0#
b1010 -
b10 .
0/

#510000
1#
1/
b1010 4
b11110 6
b1010 ;
b11110 ?
b11110 @

#520000
b0 "
0#
b0 .
0/

#530000
1#
1/

#540000
b100010 !
b100 "
0#
b100010 -
b100 .
0/

#550000
1#
1/
b100010 5
b1010 6
19
b100010 <
b1010 ?
b1010 @

#560000
b0 "
0#
b0 .
0/

#570000
1#
b1010 $
0%
1/
b1010 0
01
09

#580000
0#
0/

#581000
b100 (
b100 )

#590000
1#
1/

#600000
b10000000 !
b1 "
0#
b10000000 -
b1 .
0/

#610000
1#
1/
b10000000 3
b1110110 6
18
b10000000 :
1>
b1110110 ?
b101110110 @

#620000
b0 "
0#
b0 .
0/

#630000
1#
1/

#640000
b1 !
b10 "
0#
b1 -
b10 .
0/

#650000
1#
1/
b1 4
b1111111 6
b1 ;
1>
b1111111 ?
b101111111 @

#660000
b0 "
0#
b0 .
0/

#670000
1#
1/

#680000
b100010 !
b100 "
0#
b100010 -
b100 .
0/

#690000
1#
1/
19

#700000
b0 "
0#
b0 .
0/

#710000
1#
b1111111 $
1%
1/
b1111111 0
11
09

#720000
0#
0/

#721000
b101 (
b101 )

#730000
1#
1/

#740000
b1111111 !
b1 "
0#
b1111111 -
b1 .
0/

#750000
1#
1/
b1111111 3
b1111110 6
08
b1111111 :
0>
b1111110 ?
b1111110 @

#760000
b0 "
0#
b0 .
0/

#770000
1#
1/

#780000
b11111111 !
b10 "
0#
b11111111 -
b10 .
0/

#790000
1#
1/
b11111111 4
b10000000 6
18
b11111111 ;
1>
b10000000 ?
b10000000 @

#800000
b0 "
0#
b0 .
0/

#810000
1#
1/

#820000
b100010 !
b100 "
0#
b100010 -
b100 .
0/

#830000
1#
1/
19

#840000
b0 "
0#
b0 .
0/

#850000
1#
b10000000 $
1/
b10000000 0
09

#860000
0#
0/

#861000
b110 (
b110 )

#870000
1#
1/

#880000
b101010 !
b1 "
0#
b101010 -
b1 .
0/

#890000
1#
1/
b101010 3
b101011 6
08
b101010 :
0>
b101011 ?
b101011 @

#900000
b0 "
0#
b0 .
0/

#910000
1#
1/

#920000
b10 "
0#
b10 .
0/

#930000
1#
1/
b101010 4
b0 6
17
b101010 ;
1=
b0 ?
b0 @

#940000
b0 "
0#
b0 .
0/

#950000
1#
1/

#960000
b100010 !
b100 "
0#
b100010 -
b100 .
0/

#970000
1#
1/
19

#980000
b0 "
0#
b0 .
0/

#990000
1#
b0 $
0%
1&
1/
b0 0
01
12
09

#1000000
0#
0/

#1001000
b111 (
b111 )

#1010000
1#
1/

#1020000
b11110000 !
b1 "
0#
b11110000 -
b1 .
0/

#1030000
1#
1/
b11110000 3
b11000110 6
07
b11110000 :
0=
b11000110 ?
b111000110 @

#1040000
b0 "
0#
b0 .
0/

#1050000
1#
1/

#1060000
b10101010 !
b10 "
0#
b10101010 -
b10 .
0/

#1070000
1#
1/
b10101010 4
b1000110 6
b10101010 ;
b1000110 ?
b1000110 @

#1080000
b0 "
0#
b0 .
0/

#1090000
1#
1/

#1100000
b100100 !
b100 "
0#
b100100 -
b100 .
0/

#1110000
1#
1/
b100100 5
b10100000 6
19
b100100 <
b10100000 ?

#1120000
b0 "
0#
b0 .
0/

#1130000
1#
b10100000 $
0&
1/
b10100000 0
02
09

#1140000
0#
0/

#1141000
b1000 (
b1000 )

#1150000
1#
1/

#1160000
b11111111 !
b1 "
0#
b11111111 -
b1 .
0/

#1170000
1#
1/
b11111111 3
b10101010 6
b11111111 :
b10101010 ?

#1180000
b0 "
0#
b0 .
0/

#1190000
1#
1/

#1200000
b0 !
b10 "
0#
b0 -
b10 .
0/

#1210000
1#
1/
b0 4
b0 6
17
b0 ;
1=
b0 ?

#1220000
b0 "
0#
b0 .
0/

#1230000
1#
1/

#1240000
b100101 !
b100 "
0#
b100101 -
b100 .
0/

#1250000
1#
1/
b100101 5
b11111111 6
07
19
b100101 <
0=
b11111111 ?

#1260000
b0 "
0#
b0 .
0/

#1270000
1#
b11111111 $
1/
b11111111 0
09

#1280000
0#
0/

#1281000
b1001 (
b1001 )

#1290000
1#
1/

#1300000
b1 "
0#
b1 .
0/

#1310000
1#
1/
b100101 3
b100101 6
b100101 :
b100101 ?

#1320000
b0 "
0#
b0 .
0/

#1330000
1#
1/

#1340000
b10 "
0#
b10 .
0/

#1350000
1#
1/
b100101 4
b100101 ;
b100101 ?

#1360000
b0 "
0#
b0 .
0/

#1370000
1#
1/

#1380000
b100110 !
b100 "
0#
b100110 -
b100 .
0/

#1390000
1#
1/
b100110 5
b0 6
17
19
b100110 <
1=
b0 ?

#1400000
b0 "
0#
b0 .
0/

#1410000
1#
b0 $
1&
1/
b0 0
12
09

#1420000
0#
0/

#1421000
b1010 (
b1010 )

#1430000
1#
1/

#1440000
b0 !
b1 "
0#
b0 -
b1 .
0/

#1450000
1#
1/
b0 3
b100101 6
07
b0 :
0=
b100101 ?

#1460000
b0 "
0#
b0 .
0/

#1470000
1#
1/

#1480000
b10 "
0#
b10 .
0/

#1490000
1#
1/
b0 4
b0 6
17
b0 ;
1=
b0 ?

#1500000
b0 "
0#
b0 .
0/

#1510000
1#
1/

#1520000
b100111 !
b100 "
0#
b100111 -
b100 .
0/

#1530000
1#
1/
b100111 5
b11111111 6
07
19
b100111 <
0=
b11111111 ?

#1540000
b0 "
0#
b0 .
0/

#1550000
1#
b11111111 $
0&
1/
b11111111 0
02
09

#1560000
0#
0/

#1561000
b1011 (
b1011 )

#1570000
1#
1/

#1580000
b10000000 !
b1 "
0#
b10000000 -
b1 .
0/

#1590000
1#
1/
b10000000 3
b1111111 6
b10000000 :
b1111111 ?

#1600000
b0 "
0#
b0 .
0/

#1610000
1#
1/

#1620000
b1 !
b10 "
0#
b1 -
b10 .
0/

#1630000
1#
1/
b1 4
b1111110 6
b1 ;
b1111110 ?

#1640000
b0 "
0#
b0 .
0/

#1650000
1#
1/

#1660000
b11 !
b100 "
0#
b11 -
b100 .
0/

#1670000
1#
1/
b11 5
b11000000 6
19
b11 <
b11000000 ?

#1680000
b0 "
0#
b0 .
0/

#1690000
1#
b11000000 $
1/
b11000000 0
09

#1700000
0#
0/

#1701000
b1100 (
b1100 )

#1710000
1#
1/

#1720000
b10000000 !
b1 "
0#
b10000000 -
b1 .
0/

#1730000
1#
1/

#1740000
b0 "
0#
b0 .
0/

#1750000
1#
1/

#1760000
b1 !
b10 "
0#
b1 -
b10 .
0/

#1770000
1#
1/

#1780000
b0 "
0#
b0 .
0/

#1790000
1#
1/

#1800000
b10 !
b100 "
0#
b10 -
b100 .
0/

#1810000
1#
1/
b10 5
b1000000 6
19
b10 <
b1000000 ?

#1820000
b0 "
0#
b0 .
0/

#1830000
1#
b1000000 $
1/
b1000000 0
09

#1840000
0#
0/

#1841000
b1101 (
b1101 )

#1850000
1#
1/

#1860000
b11111111 !
b1 "
0#
b11111111 -
b1 .
0/

#1870000
1#
1/
b11111111 3
b1111111 6
b11111111 :
b1111111 ?

#1880000
b0 "
0#
b0 .
0/

#1890000
1#
1/

#1900000
b0 !
b10 "
0#
b0 -
b10 .
0/

#1910000
1#
1/
b0 4
b11111111 6
b0 ;
b11111111 ?

#1920000
b0 "
0#
b0 .
0/

#1930000
1#
1/

#1940000
b11 !
b100 "
0#
b11 -
b100 .
0/

#1950000
1#
1/
b11 5
19
b11 <
b11111111 ?

#1960000
b0 "
0#
b0 .
0/

#1970000
1#
b11111111 $
1/
b11111111 0
09

#1980000
0#
0/

#1981000
b1110 (
b1110 )

#1990000
1#
1/

#2000000
b101 !
b1 "
0#
b101 -
b1 .
0/

#2010000
1#
1/
b101 3
b101 6
b101 :
b101 ?

#2020000
b0 "
0#
b0 .
0/

#2030000
1#
1/

#2040000
b10 "
0#
b10 .
0/

#2050000
1#
1/
b101 4
b0 6
17
b101 ;
1=
b0 ?

#2060000
b0 "
0#
b0 .
0/

#2070000
1#
1/

#2080000
b111111 !
b100 "
0#
b111111 -
b100 .
0/

#2090000
1#
1/
b111111 5
19
b111111 <
1=

#2100000
b0 "
0#
b0 .
0/

#2110000
1#
b0 $
1&
1/
b0 0
12
09

#2120000
0#
0/

#2121000
b1111 (
b1111 )
b0 +
b0 ,

#2130000
1#
1/

#2140000
b10011111 !
b1 "
0#
b10011111 -
b1 .
0/

#2150000
1#
1/
b10011111 3
b10011111 :
1=

#2160000
b0 "
0#
b0 .
0/

#2170000
1#
1/

#2180000
b10101001 !
b10 "
0#
b10101001 -
b10 .
0/

#2190000
1#
1/
b10101001 4
b10101001 ;
1=

#2200000
b0 "
0#
b0 .
0/

#2210000
1#
1/

#2220000
b100000 !
b100 "
0#
b100000 -
b100 .
0/

#2230000
1#
1/
b100000 5
b1001000 6
07
18
19
b100000 <
0=
1>
b1001000 ?
b101001000 @

#2240000
b0 "
0#
b0 .
0/

#2250000
1#
b1001000 $
1%
0&
1/
b1001000 0
11
02
09

#2260000
0#
0/

#2261000
b10000 (
b10000 )
b1 ,

#2270000
1#
1/

#2280000
b1101000 !
b1 "
0#
b1101000 -
b1 .
0/

#2290000
1#
1/
b1101000 3
b10001 6
08
b1101000 :
0>
b10001 ?
b10001 @

#2300000
b0 "
0#
b0 .
0/

#2310000
1#
1/

#2320000
b11001110 !
b10 "
0#
b11001110 -
b10 .
0/

#2330000
1#
1/
b11001110 4
b110110 6
b11001110 ;
b110110 ?
b110110 @

#2340000
b0 "
0#
b0 .
0/

#2350000
1#
1/

#2360000
b100000 !
b100 "
0#
b100000 -
b100 .
0/

#2370000
1#
1/
19

#2380000
b0 "
0#
b0 .
0/

#2390000
1#
b110110 $
0%
1/
b110110 0
01
09

#2400000
0#
0/

#2401000
b10001 (
b10001 )
b10 ,

#2410000
1#
1/

#2420000
b111000 !
b1 "
0#
b111000 -
b1 .
0/

#2430000
1#
1/
b111000 3
b110 6
b111000 :
b110 ?
b110 @

#2440000
b0 "
0#
b0 .
0/

#2450000
1#
1/

#2460000
b1110000 !
b10 "
0#
b1110000 -
b10 .
0/

#2470000
1#
1/
b1110000 4
b10101000 6
18
b1110000 ;
1>
b10101000 ?
b10101000 @

#2480000
b0 "
0#
b0 .
0/

#2490000
1#
1/

#2500000
b100000 !
b100 "
0#
b100000 -
b100 .
0/

#2510000
1#
1/
19

#2520000
b0 "
0#
b0 .
0/

#2530000
1#
b10101000 $
1%
1/
b10101000 0
11
09

#2540000
0#
0/

#2541000
b10010 (
b10010 )
b11 ,

#2550000
1#
1/

#2560000
b110110 !
b1 "
0#
b110110 -
b1 .
0/

#2570000
1#
1/
b110110 3
b10100110 6
b110110 :
1>
b10100110 ?
b10100110 @

#2580000
b0 "
0#
b0 .
0/

#2590000
1#
1/

#2600000
b11101010 !
b10 "
0#
b11101010 -
b10 .
0/

#2610000
1#
1/
b11101010 4
b100000 6
08
b11101010 ;
0>
b100000 ?
b100000 @

#2620000
b0 "
0#
b0 .
0/

#2630000
1#
1/

#2640000
b100000 !
b100 "
0#
b100000 -
b100 .
0/

#2650000
1#
1/
19

#2660000
b0 "
0#
b0 .
0/

#2670000
1#
b100000 $
0%
1/
b100000 0
01
09

#2680000
0#
0/

#2681000
b10011 (
b10011 )
b100 ,

#2690000
1#
1/

#2700000
b10110101 !
b1 "
0#
b10110101 -
b1 .
0/

#2710000
1#
1/
b10110101 3
b10011111 6
b10110101 :
b10011111 ?
b110011111 @

#2720000
b0 "
0#
b0 .
0/

#2730000
1#
1/

#2740000
b1010010 !
b10 "
0#
b1010010 -
b10 .
0/

#2750000
1#
1/
b1010010 4
b111 6
b1010010 ;
b111 ?
b111 @

#2760000
b0 "
0#
b0 .
0/

#2770000
1#
1/

#2780000
b100000 !
b100 "
0#
b100000 -
b100 .
0/

#2790000
1#
1/
19

#2800000
b0 "
0#
b0 .
0/

#2810000
1#
b111 $
1/
b111 0
09

#2820000
0#
0/

#2821000
b10100 (
b10100 )
b101 ,

#2830000
1#
1/

#2840000
b10011000 !
b1 "
0#
b10011000 -
b1 .
0/

#2850000
1#
1/
b10011000 3
b11101010 6
b10011000 :
b11101010 ?
b111101010 @

#2860000
b0 "
0#
b0 .
0/

#2870000
1#
1/

#2880000
b10010011 !
b10 "
0#
b10010011 -
b10 .
0/

#2890000
1#
1/
b10010011 4
b101011 6
18
b10010011 ;
1>
b101011 ?
b100101011 @

#2900000
b0 "
0#
b0 .
0/

#2910000
1#
1/

#2920000
b100000 !
b100 "
0#
b100000 -
b100 .
0/

#2930000
1#
1/
19

#2940000
b0 "
0#
b0 .
0/

#2950000
1#
b101011 $
1%
1/
b101011 0
11
09

#2960000
0#
0/

#2961000
b10101 (
b10101 )
b110 ,

#2970000
1#
1/

#2980000
b111001 !
b1 "
0#
b111001 -
b1 .
0/

#2990000
1#
1/
b111001 3
b11001100 6
08
b111001 :
0>
b11001100 ?
b111001100 @

#3000000
b0 "
0#
b0 .
0/

#3010000
1#
1/

#3020000
b10010101 !
b10 "
0#
b10010101 -
b10 .
0/

#3030000
1#
1/
b10010101 4
b11001110 6
b10010101 ;
b11001110 ?
b111001110 @

#3040000
b0 "
0#
b0 .
0/

#3050000
1#
1/

#3060000
b100000 !
b100 "
0#
b100000 -
b100 .
0/

#3070000
1#
1/
19

#3080000
b0 "
0#
b0 .
0/

#3090000
1#
b11001110 $
0%
1/
b11001110 0
01
09

#3100000
0#
0/

#3101000
b10110 (
b10110 )
b111 ,

#3110000
1#
1/

#3120000
b10111 !
b1 "
0#
b10111 -
b1 .
0/

#3130000
1#
1/
b10111 3
b10101100 6
b10111 :
b10101100 ?
b110101100 @

#3140000
b0 "
0#
b0 .
0/

#3150000
1#
1/

#3160000
b1001001 !
b10 "
0#
b1001001 -
b10 .
0/

#3170000
1#
1/
b1001001 4
b1100000 6
b1001001 ;
b1100000 ?
b1100000 @

#3180000
b0 "
0#
b0 .
0/

#3190000
1#
1/

#3200000
b100000 !
b100 "
0#
b100000 -
b100 .
0/

#3210000
1#
1/
19

#3220000
b0 "
0#
b0 .
0/

#3230000
1#
b1100000 $
1/
b1100000 0
09

#3240000
0#
0/

#3241000
b10111 (
b10111 )
b1000 ,

#3250000
1#
1/

#3260000
b1001000 !
b1 "
0#
b1001000 -
b1 .
0/

#3270000
1#
1/
b1001000 3
b10010001 6
18
b1001000 :
1>
b10010001 ?
b10010001 @

#3280000
b0 "
0#
b0 .
0/

#3290000
1#
1/

#3300000
b11100011 !
b10 "
0#
b11100011 -
b10 .
0/

#3310000
1#
1/
b11100011 4
b101011 6
08
b11100011 ;
0>
b101011 ?
b101011 @

#3320000
b0 "
0#
b0 .
0/

#3330000
1#
1/

#3340000
b100000 !
b100 "
0#
b100000 -
b100 .
0/

#3350000
1#
1/
19

#3360000
b0 "
0#
b0 .
0/

#3370000
1#
b101011 $
1/
b101011 0
09

#3380000
0#
0/

#3381000
b11000 (
b11000 )
b1001 ,

#3390000
1#
1/

#3400000
b10010 !
b1 "
0#
b10010 -
b1 .
0/

#3410000
1#
1/
b10010 3
b11110101 6
b10010 :
b11110101 ?
b111110101 @

